[
  {
    "inputs": [],
    "stateMutability": "nonpayable",
    "type": "constructor"
  },
  {
    "inputs": [
      {
        "internalType": "address",
        "name": "target",
        "type": "address"
      }
    ],
    "name": "AddressEmptyCode",
    "type": "error"
  },
  {
    "inputs": [],
    "name": "AlreadyInitialized",
    "type": "error"
  },
  {
    "inputs": [],
    "name": "ArtifactAlreadyExists",
    "type": "error"
  },
  {
    "inputs": [
      {
        "internalType": "address",
        "name": "implementation",
        "type": "address"
      }
    ],
    "name": "ERC1967InvalidImplementation",
    "type": "error"
  },
  {
    "inputs": [],
    "name": "ERC1967NonPayable",
    "type": "error"
  },
  {
    "inputs": [],
    "name": "FailedCall",
    "type": "error"
  },
  {
    "inputs": [],
    "name": "InvalidAddress",
    "type": "error"
  },
  {
    "inputs": [],
    "name": "InvalidInitialization",
    "type": "error"
  },
  {
    "inputs": [],
    "name": "NewOwnerIsZeroAddress",
    "type": "error"
  },
  {
    "inputs": [],
    "name": "NoHandoverRequest",
    "type": "error"
  },
  {
    "inputs": [],
    "name": "NotInitializing",
    "type": "error"
  },
  {
    "inputs": [],
    "name": "UUPSUnauthorizedCallContext",
    "type": "error"
  },
  {
    "inputs": [
      {
        "internalType": "bytes32",
        "name": "slot",
        "type": "bytes32"
      }
    ],
    "name": "UUPSUnsupportedProxiableUUID",
    "type": "error"
  },
  {
    "inputs": [],
    "name": "Unauthorized",
    "type": "error"
  },
  {
    "anonymous": false,
    "inputs": [
      {
        "indexed": true,
        "internalType": "address",
        "name": "_distributionTokensAddress",
        "type": "address"
      }
    ],
    "name": "AirdropAddressChanged",
    "type": "event"
  },
  {
    "anonymous": false,
    "inputs": [
      {
        "indexed": true,
        "internalType": "address",
        "name": "_artifactBeacon",
        "type": "address"
      }
    ],
    "name": "ArtifactBeaconChanged",
    "type": "event"
  },
  {
    "anonymous": false,
    "inputs": [
      {
        "indexed": true,
        "internalType": "bytes32",
        "name": "artifactHash",
        "type": "bytes32"
      },
      {
        "indexed": true,
        "internalType": "address",
        "name": "artifactAddress",
        "type": "address"
      }
    ],
    "name": "ArtifactCreated",
    "type": "event"
  },
  {
    "anonymous": false,
    "inputs": [
      {
        "indexed": true,
        "internalType": "address",
        "name": "_escrowBeacon",
        "type": "address"
      }
    ],
    "name": "EscrowBeaconChanged",
    "type": "event"
  },
  {
    "anonymous": false,
    "inputs": [
      {
        "indexed": false,
        "internalType": "uint64",
        "name": "version",
        "type": "uint64"
      }
    ],
    "name": "Initialized",
    "type": "event"
  },
  {
    "anonymous": false,
    "inputs": [
      {
        "indexed": true,
        "internalType": "address",
        "name": "pendingOwner",
        "type": "address"
      }
    ],
    "name": "OwnershipHandoverCanceled",
    "type": "event"
  },
  {
    "anonymous": false,
    "inputs": [
      {
        "indexed": true,
        "internalType": "address",
        "name": "pendingOwner",
        "type": "address"
      }
    ],
    "name": "OwnershipHandoverRequested",
    "type": "event"
  },
  {
    "anonymous": false,
    "inputs": [
      {
        "indexed": true,
        "internalType": "address",
        "name": "_ownershipTokenBeacon",
        "type": "address"
      }
    ],
    "name": "OwnershipTokenBeaconChanged",
    "type": "event"
  },
  {
    "anonymous": false,
    "inputs": [
      {
        "indexed": true,
        "internalType": "address",
        "name": "oldOwner",
        "type": "address"
      },
      {
        "indexed": true,
        "internalType": "address",
        "name": "newOwner",
        "type": "address"
      }
    ],
    "name": "OwnershipTransferred",
    "type": "event"
  },
  {
    "anonymous": false,
    "inputs": [
      {
        "indexed": true,
        "internalType": "address",
        "name": "_rewardsBeacon",
        "type": "address"
      }
    ],
    "name": "RewardsBeaconChanged",
    "type": "event"
  },
  {
    "anonymous": false,
    "inputs": [
      {
        "indexed": true,
        "internalType": "address",
        "name": "implementation",
        "type": "address"
      }
    ],
    "name": "Upgraded",
    "type": "event"
  },
  {
    "inputs": [],
    "name": "UPGRADE_INTERFACE_VERSION",
    "outputs": [
      {
        "internalType": "string",
        "name": "",
        "type": "string"
      }
    ],
    "stateMutability": "view",
    "type": "function"
  },
  {
    "inputs": [],
    "name": "artifactBeacon",
    "outputs": [
      {
        "internalType": "address",
        "name": "",
        "type": "address"
      }
    ],
    "stateMutability": "view",
    "type": "function"
  },
  {
    "inputs": [],
    "name": "artifactCounter",
    "outputs": [
      {
        "internalType": "uint256",
        "name": "",
        "type": "uint256"
      }
    ],
    "stateMutability": "view",
    "type": "function"
  },
  {
    "inputs": [],
    "name": "artifactImpl",
    "outputs": [
      {
        "internalType": "address",
        "name": "",
        "type": "address"
      }
    ],
    "stateMutability": "view",
    "type": "function"
  },
  {
    "inputs": [],
    "name": "cancelOwnershipHandover",
    "outputs": [],
    "stateMutability": "payable",
    "type": "function"
  },
  {
    "inputs": [
      {
        "internalType": "address",
        "name": "pendingOwner",
        "type": "address"
      }
    ],
    "name": "completeOwnershipHandover",
    "outputs": [],
    "stateMutability": "payable",
    "type": "function"
  },
  {
    "inputs": [
      {
        "internalType": "bytes32",
        "name": "artifactHash",
        "type": "bytes32"
      },
      {
        "internalType": "enum ArtifactDO.ArtifactType",
        "name": "artifactType",
        "type": "uint8"
      },
      {
        "internalType": "string",
        "name": "metadata",
        "type": "string"
      },
      {
        "internalType": "string",
        "name": "repoUri",
        "type": "string"
      },
      {
        "components": [
          {
            "internalType": "address",
            "name": "owner",
            "type": "address"
          },
          {
            "internalType": "uint256",
            "name": "shares",
            "type": "uint256"
          }
        ],
        "internalType": "struct ArtifactDO.ArtifactOwner[]",
        "name": "artifactOwners",
        "type": "tuple[]"
      },
      {
        "components": [
          {
            "internalType": "address",
            "name": "ownershipTokenAddress",
            "type": "address"
          },
          {
            "internalType": "address",
            "name": "designatedTokenAddress",
            "type": "address"
          },
          {
            "internalType": "uint256",
            "name": "totalShares",
            "type": "uint256"
          },
          {
            "internalType": "string",
            "name": "tokenName",
            "type": "string"
          },
          {
            "internalType": "string",
            "name": "tokenSymbol",
            "type": "string"
          }
        ],
        "internalType": "struct ArtifactDO.ArtifactToken",
        "name": "token",
        "type": "tuple"
      },
      {
        "internalType": "uint256",
        "name": "_usageAmount",
        "type": "uint256"
      }
    ],
    "name": "createArtifact",
    "outputs": [
      {
        "internalType": "address",
        "name": "artifact",
        "type": "address"
      }
    ],
    "stateMutability": "nonpayable",
    "type": "function"
  },
  {
    "inputs": [
      {
        "internalType": "bytes32",
        "name": "artifactHash",
        "type": "bytes32"
      },
      {
        "internalType": "enum ArtifactDO.ArtifactType",
        "name": "artifactType",
        "type": "uint8"
      },
      {
        "internalType": "string",
        "name": "metadata",
        "type": "string"
      },
      {
        "internalType": "string",
        "name": "repoUri",
        "type": "string"
      },
      {
        "components": [
          {
            "internalType": "address",
            "name": "owner",
            "type": "address"
          },
          {
            "internalType": "uint256",
            "name": "shares",
            "type": "uint256"
          }
        ],
        "internalType": "struct ArtifactDO.ArtifactOwner[]",
        "name": "artifactOwners",
        "type": "tuple[]"
      },
      {
        "components": [
          {
            "internalType": "address",
            "name": "ownershipTokenAddress",
            "type": "address"
          },
          {
            "internalType": "address",
            "name": "designatedTokenAddress",
            "type": "address"
          },
          {
            "internalType": "uint256",
            "name": "totalShares",
            "type": "uint256"
          },
          {
            "internalType": "string",
            "name": "tokenName",
            "type": "string"
          },
          {
            "internalType": "string",
            "name": "tokenSymbol",
            "type": "string"
          }
        ],
        "internalType": "struct ArtifactDO.ArtifactToken",
        "name": "token",
        "type": "tuple"
      },
      {
        "internalType": "uint256",
        "name": "_usageAmount",
        "type": "uint256"
      },
      {
        "internalType": "address",
        "name": "_escrowImplementation",
        "type": "address"
      },
      {
        "internalType": "address",
        "name": "_rewardsImplementation",
        "type": "address"
      }
    ],
    "name": "createArtifact",
    "outputs": [
      {
        "internalType": "address",
        "name": "artifact",
        "type": "address"
      }
    ],
    "stateMutability": "nonpayable",
    "type": "function"
  },
  {
    "inputs": [],
    "name": "escrowBeacon",
    "outputs": [
      {
        "internalType": "address",
        "name": "",
        "type": "address"
      }
    ],
    "stateMutability": "view",
    "type": "function"
  },
  {
    "inputs": [
      {
        "internalType": "uint256",
        "name": "artifactId",
        "type": "uint256"
      }
    ],
    "name": "getArtifactAddress",
    "outputs": [
      {
        "internalType": "address",
        "name": "",
        "type": "address"
      }
    ],
    "stateMutability": "view",
    "type": "function"
  },
  {
    "inputs": [
      {
        "internalType": "bytes32",
        "name": "artifactHash",
        "type": "bytes32"
      }
    ],
    "name": "getArtifactAddressByHash",
    "outputs": [
      {
        "internalType": "address",
        "name": "",
        "type": "address"
      }
    ],
    "stateMutability": "view",
    "type": "function"
  },
  {
    "inputs": [],
    "name": "getDistributeTokensAddress",
    "outputs": [
      {
        "internalType": "address",
        "name": "",
        "type": "address"
      }
    ],
    "stateMutability": "view",
    "type": "function"
  },
  {
    "inputs": [
      {
        "internalType": "address",
        "name": "_artifactBeacon",
        "type": "address"
      },
      {
        "internalType": "address",
        "name": "_escrowBeacon",
        "type": "address"
      },
      {
        "internalType": "address",
        "name": "_rewardsBeacon",
        "type": "address"
      },
      {
        "internalType": "address",
        "name": "_ownershipTokenBeacon",
        "type": "address"
      },
      {
        "internalType": "address",
        "name": "_distributeTokens",
        "type": "address"
      },
      {
        "internalType": "address",
        "name": "_artifactImpl",
        "type": "address"
      }
    ],
    "name": "initialize",
    "outputs": [],
    "stateMutability": "nonpayable",
    "type": "function"
  },
  {
    "inputs": [],
    "name": "listAllArtifacts",
    "outputs": [
      {
        "internalType": "address[]",
        "name": "allArtifacts",
        "type": "address[]"
      }
    ],
    "stateMutability": "view",
    "type": "function"
  },
  {
    "inputs": [],
    "name": "owner",
    "outputs": [
      {
        "internalType": "address",
        "name": "result",
        "type": "address"
      }
    ],
    "stateMutability": "view",
    "type": "function"
  },
  {
    "inputs": [
      {
        "internalType": "address",
        "name": "pendingOwner",
        "type": "address"
      }
    ],
    "name": "ownershipHandoverExpiresAt",
    "outputs": [
      {
        "internalType": "uint256",
        "name": "result",
        "type": "uint256"
      }
    ],
    "stateMutability": "view",
    "type": "function"
  },
  {
    "inputs": [],
    "name": "ownershipTokenBeacon",
    "outputs": [
      {
        "internalType": "address",
        "name": "",
        "type": "address"
      }
    ],
    "stateMutability": "view",
    "type": "function"
  },
  {
    "inputs": [],
    "name": "proxiableUUID",
    "outputs": [
      {
        "internalType": "bytes32",
        "name": "",
        "type": "bytes32"
      }
    ],
    "stateMutability": "view",
    "type": "function"
  },
  {
    "inputs": [],
    "name": "renounceOwnership",
    "outputs": [],
    "stateMutability": "payable",
    "type": "function"
  },
  {
    "inputs": [],
    "name": "requestOwnershipHandover",
    "outputs": [],
    "stateMutability": "payable",
    "type": "function"
  },
  {
    "inputs": [],
    "name": "rewardsBeacon",
    "outputs": [
      {
        "internalType": "address",
        "name": "",
        "type": "address"
      }
    ],
    "stateMutability": "view",
    "type": "function"
  },
  {
    "inputs": [
      {
        "internalType": "address",
        "name": "_artifactBeacon",
        "type": "address"
      },
      {
        "internalType": "address",
        "name": "_escrowBeacon",
        "type": "address"
      },
      {
        "internalType": "address",
        "name": "_rewardsBeacon",
        "type": "address"
      },
      {
        "internalType": "address",
        "name": "_ownershipTokenBeacon",
        "type": "address"
      }
    ],
    "name": "setBeacons",
    "outputs": [],
    "stateMutability": "nonpayable",
    "type": "function"
  },
  {
    "inputs": [
      {
        "internalType": "address",
        "name": "_distributeTokensAddress",
        "type": "address"
      }
    ],
    "name": "setDistributeTokens",
    "outputs": [],
    "stateMutability": "nonpayable",
    "type": "function"
  },
  {
    "inputs": [
      {
        "internalType": "address",
        "name": "newOwner",
        "type": "address"
      }
    ],
    "name": "transferOwnership",
    "outputs": [],
    "stateMutability": "payable",
    "type": "function"
  },
  {
    "inputs": [
      {
        "internalType": "address",
        "name": "newImplementation",
        "type": "address"
      },
      {
        "internalType": "bytes",
        "name": "data",
        "type": "bytes"
      }
    ],
    "name": "upgradeToAndCall",
    "outputs": [],
    "stateMutability": "payable",
    "type": "function"
  }
]